setup.py
sobotka/__init__.py
sobotka/aws.py
sobotka/cli.py
sobotka/db.py
sobotka/file_sync_utility.py
sobotka/helpers.py
sobotka/hosts_file_manager.py
sobotka/models.py
sobotka/remote_command_runner.py
sobotka/ssh_config_file_manager.py
sobotka/yaml_util.py
sobotka.egg-info/PKG-INFO
sobotka.egg-info/SOURCES.txt
sobotka.egg-info/dependency_links.txt
sobotka.egg-info/entry_points.txt
sobotka.egg-info/requires.txt
sobotka.egg-info/top_level.txt